stable_worldmodel/__init__.py
stable_worldmodel/cli.py
stable_worldmodel/data.py
stable_worldmodel/policy.py
stable_worldmodel/spaces.py
stable_worldmodel/utils.py
stable_worldmodel/world.py
stable_worldmodel/wrappers.py
stable_worldmodel/envs/__init__.py
stable_worldmodel/envs/image_positioning.py
stable_worldmodel/envs/pusht.py
stable_worldmodel/envs/simple_point_maze.py
stable_worldmodel/envs/two_room.py
stable_worldmodel/envs/utils.py
stable_worldmodel/envs/voidrun.py
stable_worldmodel/solver/__init__.py
stable_worldmodel/solver/cem.py
stable_worldmodel/solver/gd.py
stable_worldmodel/solver/mppi.py
stable_worldmodel/solver/random.py
stable_worldmodel/solver/solver.py
stable_worldmodel/tests/test_cli.py
stable_worldmodel/tests/test_spaces.py
stable_worldmodel/tests/test_utils.py
stable_worldmodel/tests/test_world.py
stable_worldmodel/tests/solver/test_random.py
stable_worldmodel/wm/__init__.py
stable_worldmodel/wm/dinowm.py
stable_worldmodel/wm/dreamer.py
stable_worldmodel/wm/dummy.py
stable_worldmodel/wm/frame.py
stable_worldmodel/wm/old_dinowm.py
stable_worldmodel/wm/tdmpc.py
stable_worldmodel-0.0.1a0.dist-info/licenses/LICENSE
stable_worldmodel-0.0.1a0.dist-info/METADATA
stable_worldmodel-0.0.1a0.dist-info/WHEEL
stable_worldmodel-0.0.1a0.dist-info/entry_points.txt
stable_worldmodel-0.0.1a0.dist-info/top_level.txt
stable_worldmodel-0.0.1a0.dist-info/RECORD
