Metadata-Version: 2.4
Name: stable-worldmodel
Version: 0.0.1a0
Summary: Stable Library for evaluate and conduct world model research
Author: Randall Balestriero, Lucas Maes, Dan Haramati
License: MIT
Requires-Python: >=3.10
License-File: LICENSE
Requires-Dist: torch
Requires-Dist: torchvision
Requires-Dist: transformers
Requires-Dist: torchmetrics
Requires-Dist: lightning
Requires-Dist: hydra-core
Requires-Dist: loguru
Requires-Dist: tabulate
Requires-Dist: gymnasium[all]
Requires-Dist: minari
Requires-Dist: stable-pretraining
Requires-Dist: nevergrad
Requires-Dist: einops
Requires-Dist: datasets
Requires-Dist: pygame
Requires-Dist: pymunk
Requires-Dist: shapely
Provides-Extra: dev
Requires-Dist: pytest; extra == "dev"
Requires-Dist: coverage; extra == "dev"
Requires-Dist: pytest-cov; extra == "dev"
Requires-Dist: pytest-rich; extra == "dev"
Requires-Dist: codecov; extra == "dev"
Requires-Dist: pre-commit; extra == "dev"
Requires-Dist: ruff; extra == "dev"
Provides-Extra: doc
Requires-Dist: sphinx; extra == "doc"
Requires-Dist: sphinx-gallery; extra == "doc"
Requires-Dist: sphinx-book-theme; extra == "doc"
Requires-Dist: sphinxcontrib-bibtex; extra == "doc"
Requires-Dist: matplotlib; extra == "doc"
Requires-Dist: memory_profiler; extra == "doc"
Requires-Dist: furo; extra == "doc"
Requires-Dist: myst-parser; extra == "doc"
Dynamic: license-file
